sbm/__init__.py
sbm/stochastic_block_model.py
sbm-0.2.1.dist-info/LICENSE
sbm-0.2.1.dist-info/METADATA
sbm-0.2.1.dist-info/WHEEL
sbm-0.2.1.dist-info/top_level.txt
sbm-0.2.1.dist-info/RECORD
