Metadata-Version: 2.1
Name: sbm
Version: 0.2.1
Summary: Deprecated in favour of SGTL.
Home-page: UNKNOWN
Author: Peter Macgregor
Author-email: <macgregor.pr@gmail.com>
License: UNKNOWN
Keywords: python,graph,sbm,stochastic block model,algorithms
Platform: UNKNOWN
Classifier: Development Status :: 3 - Alpha
Classifier: Intended Audience :: Education
Classifier: Programming Language :: Python :: 3
Classifier: Operating System :: MacOS :: MacOS X
Classifier: Operating System :: Microsoft :: Windows
Classifier: Operating System :: POSIX :: Linux
Requires-Dist: numpy
Requires-Dist: scipy
